{
  "generated_at_utc": "2026-07-22T23:42:01.524005+00:00",
  "source": "Anexo II da Lei municipal 18.330/2025",
  "source_file": "data/raw/pgv_2026/anexo_lei_18330_2025_145975345.pdf",
  "source_sha256": "4a043e5ceb80d550e37bbdcd478cf807f74b7d51aae2742fe95938460fa39fd7",
  "output_file": "data/processed/pgv_2026_faces.csv",
  "row_format": "Codlog SQ vm2t",
  "sq_interpretation": {
    "setor": "primeiros três dígitos de SQ",
    "quadra": "últimos três dígitos de SQ"
  },
  "row_count": 184281,
  "unique_sq_count": 46826,
  "unique_codlog_count": 44934,
  "duplicate_codlog_sq_count": 0,
  "vm2t_2026": {
    "minimum": 114.0,
    "median": 1433.0,
    "maximum": 46236.0
  },
  "interpretive_status": "extração tabular da fonte oficial; a associação espacial depende de validação entre SQ/CODLOG e as geometrias cadastrais do GeoSampa"
}